ecoscape_connectivity/__init__.py
ecoscape_connectivity/distributions.py
ecoscape_connectivity/main.py
ecoscape_connectivity/repopulation.py
ecoscape_connectivity/util.py
ecoscape_connectivity-0.2.5.dist-info/licenses/LICENSE.md
ecoscape_connectivity-0.2.5.dist-info/METADATA
ecoscape_connectivity-0.2.5.dist-info/WHEEL
ecoscape_connectivity-0.2.5.dist-info/entry_points.txt
ecoscape_connectivity-0.2.5.dist-info/top_level.txt
ecoscape_connectivity-0.2.5.dist-info/RECORD
