Metadata-Version: 2.4
Name: ecoscape-connectivity
Version: 0.2.5
Summary: EcoScape habitat connectivity computation.
Author-email: Luca de Alfaro <luca@ucsc.edu>, Coen Adler <ctadler@ucsc.edu>, Artie Nazarov <anazarov@ucsc.edu>, Natalia Ocampo-Peñuela <nocampop@ucsc.edu>, Jasmine Tai <cjtai@ucsc.edu>, Natalie Valett <nvalett@ucsc.edu>
Project-URL: Homepage, https://github.com/ecoscape-earth/ecoscape-connectivity
Project-URL: Project Homepage, https://ecoscape-earth.github.io
Project-URL: Bug Tracker, https://github.com/ecoscape-earth/ecoscape-connectivity/issues
Classifier: Programming Language :: Python :: 3
Classifier: License :: OSI Approved :: BSD License
Classifier: Operating System :: OS Independent
Requires-Python: >=3.7
License-File: LICENSE.md
Requires-Dist: numpy>=1.20.3
Requires-Dist: scgt>=0.0.32
Requires-Dist: torch>=1.10.2
Dynamic: license-file
